Metadata-Version: 2.4
Name: sonnh-influxdb_clientv2
Version: 1.50.0.dev0
Summary: InfluxDB 2.0 Python client library
Home-page: https://github.com/influxdata/influxdb-client-python
Keywords: InfluxDB,InfluxDB Python Client
Classifier: Development Status :: 4 - Beta
Classifier: Intended Audience :: Developers
Classifier: License :: OSI Approved :: MIT License
Classifier: Programming Language :: Python :: 3.7
Classifier: Programming Language :: Python :: 3.8
Classifier: Programming Language :: Python :: 3.9
Classifier: Programming Language :: Python :: 3.10
Classifier: Programming Language :: Python :: 3.11
Classifier: Programming Language :: Python :: 3.12
Classifier: Topic :: Database
Classifier: Topic :: Software Development :: Libraries
Classifier: Topic :: Software Development :: Libraries :: Python Modules
Requires-Python: >=3.7
License-File: LICENSE
Requires-Dist: reactivex>=4.0.4
Requires-Dist: certifi>=14.05.14
Requires-Dist: python_dateutil>=2.5.3
Requires-Dist: urllib3>=1.26.0
Provides-Extra: extra
Requires-Dist: pandas>=1.0.0; extra == "extra"
Requires-Dist: numpy; extra == "extra"
Provides-Extra: ciso
Requires-Dist: ciso8601>=2.1.1; extra == "ciso"
Provides-Extra: async
Requires-Dist: aiohttp>=3.8.1; extra == "async"
Requires-Dist: aiocsv>=1.2.2; extra == "async"
Provides-Extra: test
Requires-Dist: flake8>=5.0.3; extra == "test"
Requires-Dist: coverage>=4.0.3; extra == "test"
Requires-Dist: nose>=1.3.7; extra == "test"
Requires-Dist: pluggy>=0.3.1; extra == "test"
Requires-Dist: py>=1.4.31; extra == "test"
Requires-Dist: randomize>=0.13; extra == "test"
Requires-Dist: pytest>=5.0.0; extra == "test"
Requires-Dist: pytest-cov>=3.0.0; extra == "test"
Requires-Dist: pytest-timeout>=2.1.0; extra == "test"
Requires-Dist: httpretty==1.0.5; extra == "test"
Requires-Dist: psutil>=5.6.3; extra == "test"
Requires-Dist: aioresponses>=0.7.3; extra == "test"
Requires-Dist: sphinx==1.8.5; extra == "test"
Requires-Dist: sphinx_rtd_theme; extra == "test"
Requires-Dist: jinja2>=3.1.4; extra == "test"
Dynamic: classifier
Dynamic: description
Dynamic: description-content-type
Dynamic: home-page
Dynamic: keywords
Dynamic: license-file
Dynamic: provides-extra
Dynamic: requires-dist
Dynamic: requires-python
Dynamic: summary
